MANIFEST.in
project_issue_sheet_view.xml
setup.py
./__init__.py
./__openerp__.py
./project_issue_sheet.py
i18n/ar.po
i18n/ca.po
i18n/cs.po
i18n/da.po
i18n/de.po
i18n/es.po
i18n/es_CR.po
i18n/es_MX.po
i18n/es_VE.po
i18n/fi.po
i18n/fr.po
i18n/gl.po
i18n/hr.po
i18n/hu.po
i18n/it.po
i18n/ja.po
i18n/lv.po
i18n/mk.po
i18n/mn.po
i18n/nl.po
i18n/pl.po
i18n/project_issue_sheet.pot
i18n/pt.po
i18n/pt_BR.po
i18n/ro.po
i18n/ru.po
i18n/sl.po
i18n/sv.po
i18n/tr.po
i18n/zh_CN.po
images/project_issue_sheet_worklog.jpeg
openerp_project_issue_sheet.egg-info/PKG-INFO
openerp_project_issue_sheet.egg-info/SOURCES.txt
openerp_project_issue_sheet.egg-info/dependency_links.txt
openerp_project_issue_sheet.egg-info/requires.txt
openerp_project_issue_sheet.egg-info/top_level.txt
security/ir.model.access.csv